README.md
setup.py
mrdflow/RNN.py
mrdflow/Sequential.py
mrdflow/__init__.py
mrdflow/activation.py
mrdflow/conv1d.py
mrdflow/conv2d.py
mrdflow/dense.py
mrdflow/embedding.py
mrdflow/init.py
mrdflow/layer.py
mrdflow/loss.py
mrdflow/lstm.py
mrdflow/model.py
mrdflow/ops.py
mrdflow/optimizer.py
mrdflow/pooling.py
mrdflow.egg-info/PKG-INFO
mrdflow.egg-info/SOURCES.txt
mrdflow.egg-info/dependency_links.txt
mrdflow.egg-info/requires.txt
mrdflow.egg-info/top_level.txt
mrdflow/autograd/__init__.py
mrdflow/autograd/conv.py
mrdflow/autograd/crector.py
mrdflow/autograd/func.py
mrdflow/autograd/ops.py
mrdflow/autograd/pooling.py
mrdflow/autograd/tensor.py
mrdflow/pytransform/__init__.py