Metadata-Version: 2.1
Name: mrdflow
Version: 1.1.0
Summary: This is a network.
Home-page: https://github.com/Zhou-chengy/mrdflow/
Author: Zhou Chengyu
Author-email: earuil@outlook.com
Maintainer: Zhou Chengyu
Maintainer-email: earuil@outlook.com
License: MIT License
Platform: all
